convexgating/__init__.py
convexgating/__main__.py
convexgating/helper.py
convexgating/hyperparameters.py
convexgating/plotting.py
convexgating/py.typed
convexgating/simulation.py
convexgating/tools.py
convexgating-1.0.0.dist-info/entry_points.txt
convexgating-1.0.0.dist-info/LICENSE
convexgating-1.0.0.dist-info/METADATA
convexgating-1.0.0.dist-info/WHEEL
convexgating-1.0.0.dist-info/RECORD
