Metadata-Version: 2.3
Name: convexgating
Version: 1.0.0
Summary: ConvexGating is a Python tool to infer optimal gating strategies for flow cytometry and cyTOF data.
License: MIT
Author: Vincent Friedrich
Author-email: vf2101@online.de
Requires-Python: >=3.9,<3.11
Classifier: License :: OSI Approved :: MIT License
Classifier: Programming Language :: Python :: 3
Classifier: Programming Language :: Python :: 3.9
Classifier: Programming Language :: Python :: 3.10
Requires-Dist: anndata (==0.10.5.post1)
Requires-Dist: array-api-compat (==1.6)
Requires-Dist: click (==8.1.7)
Requires-Dist: contourpy (==1.1.1)
Requires-Dist: cycler (==0.12.1)
Requires-Dist: fonttools (==4.51.0)
Requires-Dist: get-annotations (==0.1.2)
Requires-Dist: h5py (==3.11.0)
Requires-Dist: igraph (==0.11.4)
Requires-Dist: joblib (==1.4.0)
Requires-Dist: kiwisolver (==1.4.5)
Requires-Dist: llvmlite (==0.39.1)
Requires-Dist: markdown-it-py (==3.0.0)
Requires-Dist: matplotlib (==3.6.3)
Requires-Dist: matplotlib-venn (==0.11.10)
Requires-Dist: mdurl (==0.1.2)
Requires-Dist: natsort (==8.4.0)
Requires-Dist: networkx (==3.2.1)
Requires-Dist: numba (==0.56.4)
Requires-Dist: numpy (>=1.19.5)
Requires-Dist: packaging (==24.0)
Requires-Dist: pandas (==1.4.4)
Requires-Dist: patsy (==0.5.6)
Requires-Dist: pillow (==10.3.0)
Requires-Dist: pydot (==2.0.0)
Requires-Dist: pynndescent (==0.5.12)
Requires-Dist: pyparsing (==3.1.2)
Requires-Dist: python-dateutil (==2.9.0.post0)
Requires-Dist: python-igraph (==0.11.4)
Requires-Dist: pytz (==2024.1)
Requires-Dist: pywget (==0.31)
Requires-Dist: rich (==13.7.1)
Requires-Dist: scanpy (==1.9.6)
Requires-Dist: scikit-learn (==1.4.2)
Requires-Dist: scikit-misc (==0.1.4)
Requires-Dist: scipy (==1.10.1)
Requires-Dist: seaborn (==0.12.2)
Requires-Dist: session-info (==1.0.0)
Requires-Dist: statsmodels (>=0.14.1)
Requires-Dist: stdlib-list (==0.10.0)
Requires-Dist: texttable (==1.7.0)
Requires-Dist: threadpoolctl (==3.4.0)
Requires-Dist: tk (==0.1.0)
Requires-Dist: torch (==1.7.1)
Requires-Dist: tqdm (==4.66.2)
Requires-Dist: typing-extensions (==4.11.0)
Requires-Dist: umap-learn (==0.5.6)
Project-URL: Documentation, https://convexgating.readthedocs.io
Project-URL: Homepage, https://github.com/buettnerlab/convexgating
Project-URL: Repository, https://github.com/buettnerlab/convexgating
